synq_ai/__init__.py
synq_ai-1.0.1.dist-info/METADATA
synq_ai-1.0.1.dist-info/WHEEL
synq_ai-1.0.1.dist-info/top_level.txt
synq_ai-1.0.1.dist-info/RECORD
