Metadata-Version: 2.1
Name: synq-ai
Version: 1.0.1
Summary: [DEPRECATED] This package has been renamed to 'synqed'. Please use 'synqed' instead: https://pypi.org/project/synqed/
Home-page: https://synqlabs.ai
Author: Synq Team
Author-email: support@synq.dev
Keywords: deprecated synq synqed
Classifier: Development Status :: 7 - Inactive
Classifier: Intended Audience :: Developers
Classifier: Topic :: Software Development :: Libraries :: Python Modules
Classifier: Programming Language :: Python :: 3
Classifier: Programming Language :: Python :: 3.8
Classifier: Programming Language :: Python :: 3.9
Classifier: Programming Language :: Python :: 3.10
Classifier: Programming Language :: Python :: 3.11
Classifier: Programming Language :: Python :: 3.12
Requires-Python: >=3.8
